{"cameraMode":{"drawMode":0,"name":"Shaded","section":"Shading Mode"},"sceneLighting":true,"audioPlay":false,"sceneViewState":{"m_AlwaysRefresh":false,"showFog":true,"showSkybox":true,"showFlares":true,"showImageEffects":true,"showParticleSystems":true,"showVisualEffectGraphs":true,"m_FxEnabled":true},"in2DMode":false,"pivot":{"x":2.84439754486084,"y":-10.960478782653809,"z":-1.303483486175537},"rotation":{"x":0.13859063386917115,"y":0.8605915904045105,"z":-0.3661978244781494,"w":0.32569992542266848},"size":11.492542266845704,"orthographic":false}