{"cameraMode":{"drawMode":0,"name":"Shaded","section":"Shading Mode"},"sceneLighting":true,"audioPlay":false,"sceneViewState":{"m_AlwaysRefresh":false,"showFog":true,"showSkybox":true,"showFlares":true,"showImageEffects":true,"showParticleSystems":true,"showVisualEffectGraphs":true,"m_FxEnabled":true},"in2DMode":false,"pivot":{"x":25.18871307373047,"y":4.059815406799316,"z":8.160770416259766},"rotation":{"x":-0.0847729966044426,"y":0.8141032457351685,"z":-0.1663573533296585,"w":-0.5516604781150818},"size":0.7035627365112305,"orthographic":false}